riberry_ldap/__init__.py
riberry_ldap-0.3.0.dist-info/LICENSE
riberry_ldap-0.3.0.dist-info/WHEEL
riberry_ldap-0.3.0.dist-info/METADATA
riberry_ldap-0.3.0.dist-info/RECORD
