Metadata-Version: 2.1
Name: riberry-ldap
Version: 0.3.0
Summary: LDAP authentication for Riberry
Home-page: UNKNOWN
License: MIT
Author: Shady Rafehi
Author-email: shadyrafehi@gmail.com
Requires-Python: >=3.6,<4.0
Classifier: License :: OSI Approved :: MIT License
Classifier: Programming Language :: Python :: 3
Classifier: Programming Language :: Python :: 3.6
Classifier: Programming Language :: Python :: 3.7
Requires-Dist: ldap3 (>=2.6,<3.0)
Requires-Dist: riberry (>=0.10.0,<0.11.0)
